kitops/__init__.py
kitops/cli/__init__.py
kitops/cli/kit.py
kitops/cli/utils.py
kitops/modelkit/__init__.py
kitops/modelkit/_pydantic_kit.py
kitops/modelkit/kitfile.py
kitops/modelkit/manager.py
kitops/modelkit/reference.py
kitops/modelkit/user.py
kitops/modelkit/utils.py
kitops/py.typed
kitops-1.4.0.dist-info/METADATA
kitops-1.4.0.dist-info/WHEEL
kitops-1.4.0.dist-info/licenses/LICENSE
kitops-1.4.0.dist-info/RECORD
