Metadata-Version: 2.4
Name: kitops
Version: 1.4.0
Summary: A package for managing KitOps ModelKits and Kitfiles
License-Expression: Apache-2.0
License-File: LICENSE
Keywords: kitfile,modelkit,kitops,jozu,jozu.ml
Author: Jacob Fuss
Author-email: jacob@jozu.com
Requires-Python: >=3.10
Classifier: Programming Language :: Python :: 3
Classifier: License :: OSI Approved :: Apache Software License
Classifier: Operating System :: OS Independent
Classifier: Intended Audience :: Developers
Requires-Dist: pydantic (>=2.12,<3.0)
Requires-Dist: python-dotenv (>=1.2,<2.0)
Requires-Dist: pyyaml (>=6.0,<7.0)
Project-URL: Documentation, https://kitops.org/docs/pykitops/reference/
Project-URL: Homepage, https://github.com/jozu-ai/pykitops
Project-URL: Issues, https://github.com/jozu-ai/pykitops/issues
Project-URL: Repository, https://github.com/jozu-ai/pykitops
